dlc_generic_analysis/__init__.py
dlc_generic_analysis/_version.py
dlc_generic_analysis/analysis.py
dlc_generic_analysis/dlc.py
dlc_generic_analysis/dlc_generic_analysis.py
dlc_generic_analysis/filter.py
dlc_generic_analysis/geometries.py
dlc_generic_analysis/gui_objects.py
dlc_generic_analysis/gui_utils.py
dlc_generic_analysis/line.py
dlc_generic_analysis/math_utils.py
dlc_generic_analysis/trimmer.py
dlc_generic_analysis/utils.py
dlc_generic_analysis/video_tools.py
dlc_generic_analysis/viewer.py
dlc_generic_analysis/_tests/__init__.py
dlc_generic_analysis/_tests/test_analysis.py
dlc_generic_analysis/_tests/test_data.py
dlc_generic_analysis/_tests/test_dlc_generic_analysis.py
dlc_generic_analysis/_tests/test_filter.py
dlc_generic_analysis/_tests/test_geometries.py
dlc_generic_analysis/_tests/test_gui_objects.py
dlc_generic_analysis/_tests/test_line.py
dlc_generic_analysis/_tests/test_math_utils.py
dlc_generic_analysis/_tests/test_utils.py
dlc_generic_analysis/_tests/test_viewer.py
dlc_generic_analysis-0.0.1rc7.dist-info/LICENSE
dlc_generic_analysis-0.0.1rc7.dist-info/METADATA
dlc_generic_analysis-0.0.1rc7.dist-info/WHEEL
dlc_generic_analysis-0.0.1rc7.dist-info/top_level.txt
dlc_generic_analysis-0.0.1rc7.dist-info/RECORD
