Metadata-Version: 2.1
Name: dlc-generic-analysis
Version: 0.0.1rc7
Summary: A framework for creating analysis applications for DeepLabCut with a gui build in Qt.
Home-page: https://github.com/SurgicalPhotonics/dlc-generic-analysis
Author: Louis Adamian
Author-email: ladamian@meei.harvard.edu
License: LGPL-3.0-or-later
Classifier: Development Status :: 4 - Beta
Classifier: Intended Audience :: Developers
Classifier: Programming Language :: Python :: 3
Classifier: Programming Language :: Python :: 3.8
Classifier: Programming Language :: Python :: 3.9
Classifier: Operating System :: POSIX :: Linux
Classifier: Operating System :: Microsoft :: Windows
Classifier: Operating System :: MacOS
Classifier: License :: OSI Approved :: GNU Lesser General Public License v3 (LGPLv3)
Classifier: Natural Language :: English
Requires-Python: >=3.7
License-File: LICENSE
Requires-Dist: opencv-python-headless (>=4.1.2.30)
Requires-Dist: numpy (>=1.22.0)
Requires-Dist: pandas (>=1.3.4)
Requires-Dist: deeplabcut (>=2.2.0.3)
Requires-Dist: tqdm (>=4.62.3)
Requires-Dist: matplotlib (>=3.5.0)
Requires-Dist: moviepy (>=1.0.3)
Requires-Dist: scipy (>=1.7.3)
Requires-Dist: tables (>=3.6.0)
Provides-Extra: gui
Requires-Dist: PySide2 (>=5.15.2) ; extra == 'gui'
Requires-Dist: QtPy (>=1.11.2) ; extra == 'gui'
Requires-Dist: QtAwesome (>=1.1.1) ; extra == 'gui'
Provides-Extra: pyqt5
Requires-Dist: PyQt5 (>=5.15.6) ; extra == 'pyqt5'
Requires-Dist: QtPy (>=1.11.2) ; extra == 'pyqt5'
Requires-Dist: QtAwesome (>=1.1.1) ; extra == 'pyqt5'
Provides-Extra: pyqt6
Requires-Dist: PyQt6 (>=6.2.3) ; extra == 'pyqt6'
Requires-Dist: QtPy (>=1.11.2) ; extra == 'pyqt6'
Requires-Dist: QtAwesome (>=1.1.1) ; extra == 'pyqt6'
Provides-Extra: pyside2
Requires-Dist: PySide2 (>=5.15.2) ; extra == 'pyside2'
Requires-Dist: QtPy (>=1.11.2) ; extra == 'pyside2'
Requires-Dist: QtAwesome (>=1.1.1) ; extra == 'pyside2'
Provides-Extra: pyside6
Requires-Dist: PySide6 (>=6.2.3) ; extra == 'pyside6'
Requires-Dist: QtPy (>=1.11.2) ; extra == 'pyside6'
Requires-Dist: QtAwesome (>=1.1.1) ; extra == 'pyside6'
